{
  "1924950": {
    "product_id": "3",
    "product_name": "icecream",
    "username": "abhishek"
  },
  "2416373": {
    "product_id": "1",
    "product_name": "soap",
    "username": "adarshrawat"
  },
  "4442665": {
    "product_id": "1",
    "product_name": "soap",
    "username": "adarshrawat"
  },
  "5122163": {
    "product_id": "3",
    "product_name": "toothpaste",
    "quantity": 100,
    "username": "adarshrawat"
  },
  "5514048": {
    "product_id": "3",
    "product_name": "toothpaste",
    "username": "abhishek"
  },
  "5915434": {
    "product_id": "3",
    "product_name": "icecream",
    "username": "abhishek"
  },
  "6475813": {
    "product_id": "3",
    "product_name": "icecream",
    "username": "abhishek"
  },
  "6726490": {
    "product_id": "4",
    "product_name": "detergent",
    "username": "adarshrawat"
  },
  "6858615": {
    "product_id": "1",
    "product_name": "soap",
    "username": "adarshrawat"
  },
  "7012512": {
    "product_id": "3",
    "product_name": "toothpaste",
    "username": "abhishek"
  },
  "8342100": {
    "product_id": "1",
    "product_name": "soap",
    "username": "abhishek"
  }
}